html_login_field_detector-0.1.6.data/data/dataset/training_urls.json
html_login_field_detector-0.1.6.data/data/docs/README.md
login_field_detector/__init__.py
login_field_detector/field_detector.py
login_field_detector/html_feature_extractor.py
login_field_detector/html_fetcher.py
login_field_detector/keywords.json
html_login_field_detector-0.1.6.dist-info/LICENSE
html_login_field_detector-0.1.6.dist-info/METADATA
html_login_field_detector-0.1.6.dist-info/WHEEL
html_login_field_detector-0.1.6.dist-info/top_level.txt
html_login_field_detector-0.1.6.dist-info/RECORD
