Metadata-Version: 2.1
Name: html-login-field-detector
Version: 0.1.6
Summary: A library for detecting login fields in HTML using DistilBERT.
Author-email: Victor Delaplaine <vdelaplainess@gmail.com>
License: MIT
Project-URL: homepage, https://github.com/ByVictorrr
Project-URL: repository, https://github.com/ByVictorrr/LoginFieldDetector
Project-URL: documentation, https://byvictorrr.github.io/LoginFieldDetector/
Classifier: Programming Language :: Python :: 3
Classifier: License :: OSI Approved :: MIT License
Classifier: Operating System :: OS Independent
Requires-Python: >=3.10
License-File: LICENSE
Requires-Dist: transformers>=4.33.0
Requires-Dist: datasets>=2.14.0
Requires-Dist: beautifulsoup4>=4.11.0
Requires-Dist: diskcache>=5.6.0
Requires-Dist: huggingface_hub>=0.15.0
Requires-Dist: scikit-learn>=1.1.0
Requires-Dist: matplotlib>=3.5.0
Requires-Dist: lxml>=4.8.0
Requires-Dist: lxml_html_clean>=0.4.0
Requires-Dist: certifi>=2024.6.0
Requires-Dist: tensorboard>=2.17.0
Requires-Dist: babel>=2.8.0
Requires-Dist: fake-useragent>=1.5.1
Requires-Dist: playwright==1.39.0
Requires-Dist: playwright-stealth>=1.0.4
Provides-Extra: cpu
Requires-Dist: torch>=2.0.0; extra == "cpu"
Requires-Dist: torchvision>=0.15.0; extra == "cpu"
Requires-Dist: torchaudio>=2.0.0; extra == "cpu"
Provides-Extra: gpu
Requires-Dist: torch==2.5.1+cu118; extra == "gpu"
Requires-Dist: torchvision==0.20.1+cu118; extra == "gpu"
Requires-Dist: torchaudio==2.5.1+cu118; extra == "gpu"
Provides-Extra: docs
Requires-Dist: sphinx>=7.2; extra == "docs"
Requires-Dist: sphinxcontrib-napoleon; extra == "docs"
Requires-Dist: sphinx-rtd-theme; extra == "docs"
Provides-Extra: test
Requires-Dist: pytest; extra == "test"
Requires-Dist: pytest-cov; extra == "test"
